fablab/__init__.py
fablab/common.py
fablab/loaders.py
fablab/savers.py
fablab/utils.py
fablab-0.0.2.dist-info/LICENSE
fablab-0.0.2.dist-info/METADATA
fablab-0.0.2.dist-info/WHEEL
fablab-0.0.2.dist-info/top_level.txt
fablab-0.0.2.dist-info/RECORD
